{
    "run_history": {
        "15m": {
            "run_start": "2026-07-03 11:19:32 IST",
            "duration_seconds": 25.151193
        }
    },
    "data": [
        {
            "symbol": "RECLTD.NS",
            "timeframe": "15m",
            "trend": "Inside Trend",
            "breakout_dt": "",
            "triggered_at": ""
        },
        {
            "symbol": "SOUTHBANK.NS",
            "timeframe": "15m",
            "trend": "Inside Trend",
            "breakout_dt": "",
            "triggered_at": ""
        },
        {
            "symbol": "CHOLAFIN.NS",
            "timeframe": "15m",
            "trend": "Inside Trend",
            "breakout_dt": "",
            "triggered_at": ""
        },
        {
            "symbol": "PHARMABEES.NS",
            "timeframe": "15m",
            "trend": "Buy Trend",
            "breakout_dt": "2026-07-03 09:30",
            "triggered_at": "2026-07-03 11:19:32 IST"
        },
        {
            "symbol": "APOLLOHOSP.NS",
            "timeframe": "15m",
            "trend": "Buy Trend",
            "breakout_dt": "2026-07-03 09:15",
            "triggered_at": "2026-07-03 11:19:32 IST"
        },
        {
            "symbol": "JUNIORBEES.NS",
            "timeframe": "15m",
            "trend": "Inside Trend",
            "breakout_dt": "",
            "triggered_at": ""
        }
    ]
}